dbpl/__init__.py
dbpl/dbpl.py
dbpl-1.0.1.dist-info/LICENSE
dbpl-1.0.1.dist-info/METADATA
dbpl-1.0.1.dist-info/WHEEL
dbpl-1.0.1.dist-info/top_level.txt
dbpl-1.0.1.dist-info/RECORD
