Metadata-Version: 2.1
Name: dbpl
Version: 1.0.1
Summary: UNKNOWN
Home-page: https://github.com/gch1p/deadbeef-playlist.git
Author: Evgeny Zinoviev
Author-email: me@ch1p.io
License: BSD
Project-URL: Bug Tracker, https://github.com/gch1p/deadbeef-playlist/issues
Platform: UNKNOWN
Classifier: Programming Language :: Python :: 3
Classifier: License :: OSI Approved :: BSD License
Classifier: Operating System :: OS Independent
Requires-Python: >=3.6
